{"pagination":{"pageCount":14,"total":275},"results":[{"id":4216,"name":"JAS Super Form'","compte":"1","isSubscribed":false,"urls":{"long":"/salle/4216,jas-super-form,club-de-fitness,noisy-le-grand,93160,fr"},"searchPicture":{"url":"https://datas.masalledesport.com/prod/null"},"type":{"id":1,"name":"Club de fitness"},"address":{"street":"4 allée Maintenon","zipCode":"93160","city":"NOISY LE GRAND","country":{"code":"FR"}},"location":{"lat":48.8498351,"lng":2.5579435},"description":{},"pass":{"key":"1Seance","shortDescription":"Recevez 1 séance d'essai GRATUITE","description":"Recevez votre séance d'essai GRATUITE par email !","free":true},"reviews":{"count":0,"avg":null},"openingHours":{},"products":[],"distance":3729,"services":[],"comforts":[],"equipments":[],"activities":[],"access":{}},{"id":8814,"name":"NARAI GYM","compte":"1","isSubscribed":false,"urls":{"long":"/salle/8814,narai-gym,club-de-sport-art-martiaux-combat,paris,75020,fr"},"searchPicture":{"url":"https://datas.masalledesport.com/prod/null"},"type":{"id":6,"name":"Club de sport art-martiaux / combat"},"address":{"street":"30, rue du Borrégo","zipCode":"75020","city":"PARIS","country":{"code":"FR"}},"location":{"lat":48.8729088,"lng":2.40050689999998},"description":{},"pass":{"key":"cours_gratuit","shortDescription":"Recevez 1 cours d'essai GRATUIT","description":"Bénéficiez d'un cours d'essai gratuit !","free":true},"reviews":{"count":0,"avg":null},"openingHours":{},"products":[],"distance":3729,"services":[],"comforts":[],"equipments":[],"activities":[],"access":{}},{"id":414,"name":"Club Rem Gym Paris 19","compte":"1","isSubscribed":false,"urls":{"long":"/salle/414,club-rem-gym-paris-19,club-de-fitness,paris,75019,fr"},"searchPicture":{"url":"https://datas.masalledesport.com/prod/place/414/searchPicture/1507289489619.jpeg","originalUrl":"picsData/salles/galeries/414-3343-800x600.jpg","imageProcess":"big-01"},"type":{"id":1,"name":"Club de fitness"},"address":{"street":"72 rue de Romainville","zipCode":"75019","city":"PARIS","country":{"code":"FR"}},"location":{"lat":48.8772620438609,"lng":2.40336656570435},"description":{},"pass":{"key":"1Seance","shortDescription":"Recevez 1 séance d'essai GRATUITE","description":"Recevez votre séance d'essai GRATUITE par email !","free":true},"reviews":{"count":1,"avg":5},"openingHours":{},"products":[],"distance":3743,"services":[],"comforts":[],"equipments":[],"activities":[],"access":{}},{"id":6345,"name":"Soir de Danse","compte":"1","isSubscribed":false,"urls":{"long":"/salle/6345,soir-de-danse,ecole-de-danse,le-raincy,93340,fr"},"searchPicture":{"url":"https://datas.masalledesport.com/prod/null"},"type":{"id":7,"name":"Ecole de danse"},"address":{"street":"72 allée du Jardin Anglais","zipCode":"93340","city":"LE RAINCY","country":{"code":"FR"}},"location":{"lat":48.8995401789407,"lng":2.51451730728149},"description":{},"pass":{"key":"1Seance","shortDescription":"Recevez 1 séance d'essai GRATUITE","description":"Recevez votre séance d'essai GRATUITE par email !","free":true},"reviews":{"count":0,"avg":null},"openingHours":{},"products":[],"distance":3749,"services":[],"comforts":[],"equipments":[],"activities":[],"access":{}},{"id":2120,"name":"Danser la Vie Saint Maur des Fosses","compte":"1","isSubscribed":false,"urls":{"long":"/salle/2120,danser-la-vie-saint-maur-des-fosses,ecole-de-danse,saint-maur-des-fosses,94100,fr"},"searchPicture":{"url":"https://datas.masalledesport.com/prod/null"},"type":{"id":7,"name":"Ecole de danse"},"address":{"street":"137 boulevard Créteil","zipCode":"94100","city":"SAINT MAUR DES FOSSES","country":{"code":"FR"}},"location":{"lat":48.797972,"lng":2.4925487},"description":{},"pass":{"key":"1Seance","shortDescription":"Recevez 1 séance d'essai GRATUITE","description":"Recevez votre séance d'essai GRATUITE par email !","free":true},"reviews":{"count":0,"avg":null},"openingHours":{},"products":[],"distance":3775,"services":[],"comforts":[],"equipments":[],"activities":[],"access":{}},{"id":2248,"name":"Yoga Center Nation","compte":"1","isSubscribed":false,"urls":{"long":"/salle/2248,yoga-center-nation,studio-yoga-pilates,paris,75011,fr"},"searchPicture":{"url":"https://datas.masalledesport.com/prod/null"},"type":{"id":11,"name":"Studio Yoga / Pilates"},"address":{"street":"2 passage Turquetil","zipCode":"75011","city":"PARIS","country":{"code":"FR"}},"location":{"lat":48.851369,"lng":2.392729},"description":{},"pass":{"key":"1Seance","shortDescription":"Recevez 1 séance d'essai GRATUITE","description":"Recevez votre séance d'essai GRATUITE par email !","free":true},"reviews":{"count":0,"avg":null},"openingHours":{},"products":[],"distance":3779,"services":[],"comforts":[],"equipments":[],"activities":[],"access":{}},{"id":2127,"name":"Centre de Danse Eric Sourdeau","compte":"1","isSubscribed":false,"urls":{"long":"/salle/2127,centre-de-danse-eric-sourdeau,ecole-de-danse,saint-maur-des-fosses,94100,fr"},"searchPicture":{"url":"https://datas.masalledesport.com/prod/null"},"type":{"id":7,"name":"Ecole de danse"},"address":{"street":"32 rue Bir Hakeim","zipCode":"94100","city":"SAINT MAUR DES FOSSES","country":{"code":"FR"}},"location":{"lat":48.796235,"lng":2.477044},"description":{},"pass":{"key":"1Seance","shortDescription":"Recevez 1 séance d'essai GRATUITE","description":"Recevez votre séance d'essai GRATUITE par email !","free":true},"reviews":{"count":0,"avg":null},"openingHours":{},"products":[],"distance":3819,"services":[],"comforts":[],"equipments":[],"activities":[],"access":{}},{"id":7393,"name":"Orty Gym","compte":"1","isSubscribed":false,"urls":{"long":"/salle/7393,orty-gym,salle-de-fitness-100-femmes,le-raincy,93340,fr"},"searchPicture":{"url":"https://datas.masalledesport.com/prod/null"},"type":{"id":3,"name":"Salle de fitness 100% femmes"},"address":{"street":"9 avenue Thiers","zipCode":"93340","city":"LE RAINCY","country":{"code":"FR"}},"location":{"lat":48.9015477,"lng":2.5120326},"description":{},"pass":{"key":"1Seance","shortDescription":"Recevez 1 séance d'essai GRATUITE","description":"Recevez votre séance d'essai GRATUITE par email !","free":true},"reviews":{"count":0,"avg":null},"openingHours":{},"products":[],"distance":3823,"services":[],"comforts":[],"equipments":[],"activities":[],"access":{}},{"id":2111,"name":"Centre Artistique Zaza","compte":"1","isSubscribed":false,"urls":{"long":"/salle/2111,centre-artistique-zaza,ecole-de-danse,pantin,93500,fr"},"searchPicture":{"url":"https://datas.masalledesport.com/prod/null"},"type":{"id":7,"name":"Ecole de danse"},"address":{"street":"9 bis rue François Arago","zipCode":"93500","city":"PANTIN","country":{"code":"FR"}},"location":{"lat":48.8923423,"lng":2.4177038},"description":{},"pass":{"key":"1Seance","shortDescription":"Recevez 1 séance d'essai GRATUITE","description":"Recevez votre séance d'essai GRATUITE par email !","free":true},"reviews":{"count":0,"avg":null},"openingHours":{},"products":[],"distance":3863,"services":[],"comforts":[],"equipments":[],"activities":[],"access":{}},{"id":8677,"name":"L'Orange Bleue Le Pré St Gervais","compte":"1","isSubscribed":false,"urls":{"long":"/salle/8677,l-orange-bleue-le-pre-st-gervais,club-de-fitness,le-pre-saint-gervais,93310,fr"},"searchPicture":{"url":"https://datas.masalledesport.com/prod/null"},"type":{"id":1,"name":"Club de fitness"},"address":{"street":"35 rue Louis Blanc","zipCode":"93310","city":"LE PRÉ SAINT GERVAIS","country":{"code":"FR"}},"location":{"lat":48.8860731,"lng":2.40873590000001},"description":{},"pass":{"key":"1Seance","shortDescription":"Recevez 1 séance d'essai GRATUITE","description":"Recevez votre séance d'essai GRATUITE par email !","free":true},"reviews":{"count":0,"avg":null},"openingHours":{},"products":[],"distance":3872,"services":[],"comforts":[],"equipments":[],"activities":[],"access":{}},{"id":9782,"name":"Magic Form Créteil","compte":"1","isSubscribed":false,"urls":{"long":"/salle/9782,magic-form-creteil,club-de-fitness,creteil,94000,fr"},"searchPicture":{"url":"https://datas.masalledesport.com/prod/place/9782/searchPicture/1507295769254.jpeg","originalUrl":"picsData/salles/galeries/9782-19083-800x600.jpg","imageProcess":"big-01"},"type":{"id":1,"name":"Club de fitness"},"address":{"street":"20 avenue du marechal de lattre de tassigny","zipCode":"94000","city":"CRÉTEIL","country":{"code":"FR"}},"location":{"lat":48.7964862,"lng":2.4582335000000057},"description":{},"pass":{"key":"1Seance","shortDescription":"Recevez 1 séance d'essai GRATUITE","description":"Recevez votre séance d'essai GRATUITE par email !","free":true},"reviews":{"count":0,"avg":null},"openingHours":{},"products":[{"id":5152,"msdsPrice":10,"publicPrice":15,"shortName":"1 entrée","fullName":"1 entrée","shopUrl":"https://shop.masalledesport.com/product/5152","reduction":33},{"id":5153,"msdsPrice":40,"publicPrice":75,"shortName":"5 entrées","fullName":"5 entrées","shopUrl":"https://shop.masalledesport.com/product/5153","reduction":46},{"id":5154,"msdsPrice":80,"publicPrice":100,"shortName":"1 mois","fullName":"1 mois","shopUrl":"https://shop.masalledesport.com/product/5154","reduction":20}],"distance":3885,"services":[],"comforts":[],"equipments":[],"activities":[],"access":{}},{"id":2257,"name":"Bien Etre à Paris","compte":"1","isSubscribed":false,"urls":{"long":"/salle/2257,bien-etre-a-paris,club-de-fitness,paris,75020,fr"},"searchPicture":{"url":"https://datas.masalledesport.com/prod/null"},"type":{"id":1,"name":"Club de fitness"},"address":{"street":"114 rue de Ménilmontant","zipCode":"75020","city":"PARIS","country":{"code":"FR"}},"location":{"lat":48.8698597,"lng":2.3940573},"description":{},"pass":{"key":"1Seance","shortDescription":"Recevez 1 séance d'essai GRATUITE","description":"Recevez votre séance d'essai GRATUITE par email !","free":true},"reviews":{"count":0,"avg":null},"openingHours":{},"products":[],"distance":3927,"services":[],"comforts":[],"equipments":[],"activities":[],"access":{}},{"id":8278,"name":"Centre de Danse Payaud","compte":"1","isSubscribed":false,"urls":{"long":"/salle/8278,centre-de-danse-payaud,ecole-de-danse,creteil,94000,fr"},"searchPicture":{"url":"https://datas.masalledesport.com/prod/place/8278/searchPicture/1507293459167.jpeg","originalUrl":"picsData/salles/galeries/8278-9174-800x600.jpg","imageProcess":"big-01"},"type":{"id":7,"name":"Ecole de danse"},"address":{"street":"13bis avenue du Maréchal de Lattre de Tassigny","zipCode":"94000","city":"CRéTEIL","country":{"code":"FR"}},"location":{"lat":48.7956623,"lng":2.45787340000004},"description":{},"pass":{"key":"cours_gratuit","shortDescription":"Recevez 1 cours d'essai GRATUIT","description":"Bénéficiez d'un cours d'essai gratuit !","free":true},"reviews":{"count":0,"avg":null},"openingHours":{},"products":[],"distance":3944,"services":[],"comforts":[],"equipments":[],"activities":[],"access":{}},{"id":6334,"name":"Aquabiking","compte":"1","isSubscribed":false,"urls":{"long":"/salle/6334,aquabiking,centre-d-aquabike-aquabiking,alfortville,94140,fr"},"searchPicture":{"url":"https://datas.masalledesport.com/prod/null"},"type":{"id":9,"name":"Centre d'Aquabike / Aquabiking"},"address":{"street":"38 rue du Marché","zipCode":"94140","city":"ALFORTVILLE","country":{"code":"FR"}},"location":{"lat":48.8089579,"lng":2.4171743},"description":{},"pass":{"key":"1Seance","shortDescription":"Recevez 1 séance d'essai GRATUITE","description":"Recevez votre séance d'essai GRATUITE par email !","free":true},"reviews":{"count":0,"avg":null},"openingHours":{},"products":[],"distance":3971,"services":[],"comforts":[],"equipments":[],"activities":[],"access":{}},{"id":7716,"name":"Yoga pour Tous, Association Yoga en Val de Marne","compte":"1","isSubscribed":false,"urls":{"long":"/salle/7716,yoga-pour-tous-association-yoga-en-val-de-marne,studio-yoga-pilates,creteil,94000,fr"},"searchPicture":{"url":"https://datas.masalledesport.com/prod/place/7716/searchPicture/1507292792809.jpeg","originalUrl":"picsData/salles/galeries/7716-6993-800x600.jpg","imageProcess":"big-01"},"type":{"id":11,"name":"Studio Yoga / Pilates"},"address":{"street":"18 avenue de la Ferme","zipCode":"94000","city":"CRETEIL","country":{"code":"FR"}},"location":{"lat":48.7950069,"lng":2.4585654},"description":{},"pass":{"key":"cours_gratuit","shortDescription":"Recevez 1 cours d'essai GRATUIT","description":"Bénéficiez d'un cours d'essai gratuit !","free":true},"reviews":{"count":0,"avg":null},"openingHours":{},"products":[],"distance":3982,"services":[],"comforts":[],"equipments":[],"activities":[],"access":{}},{"id":2302,"name":"Association Médecine et Yoga","compte":"1","isSubscribed":false,"urls":{"long":"/salle/2302,association-medecine-et-yoga,salle-de-gym-bien-etre,la-varenne-saint-hilaire,94210,fr"},"searchPicture":{"url":"https://datas.masalledesport.com/prod/null"},"type":{"id":4,"name":"Salle de gym / bien être"},"address":{"street":"8 bis avenue de la Révolution Française","zipCode":"94210","city":"LA VARENNE SAINT HILAIRE","country":{"code":"FR"}},"location":{"lat":48.7966815,"lng":2.5041959},"description":{},"pass":{"key":"1Seance","shortDescription":"Recevez 1 séance d'essai GRATUITE","description":"Recevez votre séance d'essai GRATUITE par email !","free":true},"reviews":{"count":0,"avg":null},"openingHours":{},"products":[],"distance":4000,"services":[],"comforts":[],"equipments":[],"activities":[],"access":{}},{"id":9224,"name":"Art Boxing Club","compte":"1","isSubscribed":false,"urls":{"long":"/salle/9224,art-boxing-club,coach-sportif,paris,75011,fr"},"searchPicture":{"url":"https://datas.masalledesport.com/prod/place/9224/searchPicture/1507294923945.jpeg","originalUrl":"picsData/salles/galeries/9224-15672-800x600.jpg","imageProcess":"big-01"},"type":{"id":8,"name":"Coach sportif"},"address":{"street":"26 rue de la Folie Regnault","zipCode":"75011","city":"Paris","country":{"code":"FR"}},"location":{"lat":48.857774,"lng":2.387909000000036},"description":{},"pass":{"key":"1Seance","shortDescription":"Recevez 1 séance d'essai GRATUITE","description":"Recevez votre séance d'essai GRATUITE par email !","free":true},"reviews":{"count":0,"avg":null},"openingHours":{},"products":[],"distance":4021,"services":[],"comforts":[],"equipments":[],"activities":[],"access":{}},{"id":9239,"name":"U-PERCUTE, Art Boxing Club","compte":"1","isSubscribed":false,"urls":{"long":"/salle/9239,u-percute-art-boxing-club,club-de-sport-art-martiaux-combat,paris,75011,fr"},"searchPicture":{"url":"https://datas.masalledesport.com/prod/place/9239/searchPicture/1507294952175.jpeg","originalUrl":"picsData/salles/galeries/9239-15759-800x600.jpg","imageProcess":"big-01"},"type":{"id":6,"name":"Club de sport art-martiaux / combat"},"address":{"street":"26 rue de la Folie Regnault","zipCode":"75011","city":"PARIS","country":{"code":"FR"}},"location":{"lat":48.857774,"lng":2.387909000000036},"description":{},"pass":{"key":"1Seance","shortDescription":"Recevez 1 séance d'essai GRATUITE","description":"Recevez votre séance d'essai GRATUITE par email !","free":true},"reviews":{"count":0,"avg":null},"openingHours":{},"products":[],"distance":4021,"services":[],"comforts":[],"equipments":[],"activities":[],"access":{}},{"id":5080,"name":"Bolly Deewani","compte":"1","isSubscribed":false,"urls":{"long":"/salle/5080,bolly-deewani,salle-de-gym-bien-etre,paris,75012,fr"},"searchPicture":{"url":"https://datas.masalledesport.com/prod/null"},"type":{"id":4,"name":"Salle de gym / bien être"},"address":{"street":"","zipCode":"75012","city":"PARIS","country":{"code":"FR"}},"location":{"lat":48.8408083,"lng":2.3881833},"description":{},"pass":{"key":"1Seance","shortDescription":"Recevez 1 séance d'essai GRATUITE","description":"Recevez votre séance d'essai GRATUITE par email !","free":true},"reviews":{"count":0,"avg":null},"openingHours":{},"products":[],"distance":4054,"services":[],"comforts":[],"equipments":[],"activities":[],"access":{}},{"id":4924,"name":"Groupe Raizes de Dois Capoeiras","compte":"1","isSubscribed":false,"urls":{"long":"/salle/4924,groupe-raizes-de-dois-capoeiras,club-de-sport-art-martiaux-combat,charenton-le-pont,94220,fr"},"searchPicture":{"url":"https://datas.masalledesport.com/prod/null"},"type":{"id":6,"name":"Club de sport art-martiaux / combat"},"address":{"street":"7 B quai de Bercy","zipCode":"94220","city":"CHARENTON LE PONT","country":{"code":"FR"}},"location":{"lat":48.8221306,"lng":2.398644},"description":{},"pass":{"key":"1Seance","shortDescription":"Recevez 1 séance d'essai GRATUITE","description":"Recevez votre séance d'essai GRATUITE par email !","free":true},"reviews":{"count":0,"avg":null},"openingHours":{},"products":[],"distance":4056,"services":[],"comforts":[],"equipments":[],"activities":[],"access":{}}]}