{"pagination":{"pageCount":13,"total":242},"results":[{"id":5891,"name":"Sant\u00e9 Fitness Bourg La Reine","compte":"1","isSubscribed":false,"urls":{"long":"\/salle\/5891,sante-fitness-bourg-la-reine,club-de-fitness,bourg-la-reine,92340,fr"},"searchPicture":{"url":"https:\/\/datas.masalledesport.com\/prod\/null"},"type":{"id":1,"name":"Club de fitness"},"address":{"street":"21 rue Andr\u00e9 Theuriet","zipCode":"92340","city":"BOURG LA REINE","country":{"code":"FR"}},"location":{"lat":48.77770970000000261279637925326824188232421875,"lng":2.3124576000000001130274540628306567668914794921875},"description":[],"pass":{"key":"1Seance","shortDescription":"Recevez 1 s\u00e9ance d'essai GRATUITE","description":"Recevez votre s\u00e9ance d'essai GRATUITE par email !","free":true},"reviews":{"count":19,"avg":4.78947368421052654952063676319085061550140380859375},"openingHours":[],"products":[],"distance":1420,"services":[],"comforts":[],"equipments":[],"activities":[],"access":[]},{"id":4867,"name":"Gym Loisirs","compte":"1","isSubscribed":false,"urls":{"long":"\/salle\/4867,gym-loisirs,salle-de-gym-bien-etre,clamart,92140,fr"},"searchPicture":{"url":"https:\/\/datas.masalledesport.com\/prod\/null"},"type":{"id":4,"name":"Salle de gym \/ bien \u00eatre"},"address":{"street":"28 rue Lazare Carnot","zipCode":"92140","city":"CLAMART","country":{"code":"FR"}},"location":{"lat":48.80911290000000235522747971117496490478515625,"lng":2.272632600000000113737996798590756952762603759765625},"description":[],"pass":{"key":"1Seance","shortDescription":"Recevez 1 s\u00e9ance d'essai GRATUITE","description":"Recevez votre s\u00e9ance d'essai GRATUITE par email !","free":true},"reviews":{"count":0,"avg":null},"openingHours":[],"products":[],"distance":1490,"services":[],"comforts":[],"equipments":[],"activities":[],"access":[]},{"id":9055,"name":"Body Next","compte":"1","isSubscribed":false,"urls":{"long":"\/salle\/9055,body-next,club-de-fitness,le-plessis-robinson,92350,fr"},"searchPicture":{"url":"https:\/\/datas.masalledesport.com\/prod\/place\/9055\/searchPicture\/1507294832525.jpeg","originalUrl":"picsData\/salles\/galeries\/9055-15365-800x600.jpg","imageProcess":"big-01"},"type":{"id":1,"name":"Club de fitness"},"address":{"street":"82 bis, Avenue Charles de Gaulle","zipCode":"92350","city":"LE PLESSIS ROBINSON","country":{"code":"FR"}},"location":{"lat":48.776948099999998476050677709281444549560546875,"lng":2.2574180000000296786311082541942596435546875},"description":[],"pass":{"key":"1Seance","shortDescription":"Recevez 1 s\u00e9ance d'essai GRATUITE","description":"Recevez votre s\u00e9ance d'essai GRATUITE par email !","free":true},"reviews":{"count":0,"avg":null},"openingHours":[],"products":[],"distance":1618,"services":[],"comforts":[],"equipments":[],"activities":[],"access":[]},{"id":7962,"name":"FEKSD Cachan Krav Maga","compte":"1","isSubscribed":false,"urls":{"long":"\/salle\/7962,feksd-cachan-krav-maga,club-de-sport-art-martiaux-combat,cachan,94230,fr"},"searchPicture":{"url":"https:\/\/datas.masalledesport.com\/prod\/null"},"type":{"id":6,"name":"Club de sport art-martiaux \/ combat"},"address":{"street":"Avenue du Pr\u00e9sident Wilson","zipCode":"94230","city":"CACHAN","country":{"code":"FR"}},"location":{"lat":48.789424328254398233184474520385265350341796875,"lng":2.32705105609738982508361004875041544437408447265625},"description":[],"pass":{"key":"1Seance","shortDescription":"Recevez 1 s\u00e9ance d'essai GRATUITE","description":"Recevez votre s\u00e9ance d'essai GRATUITE par email !","free":true},"reviews":{"count":0,"avg":null},"openingHours":[],"products":[],"distance":1814,"services":[],"comforts":[],"equipments":[],"activities":[],"access":[]},{"id":5147,"name":"Connexion Swing","compte":"1","isSubscribed":false,"urls":{"long":"\/salle\/5147,connexion-swing,ecole-de-danse,montrouge,92120,fr"},"searchPicture":{"url":"https:\/\/datas.masalledesport.com\/prod\/null"},"type":{"id":7,"name":"Ecole de danse"},"address":{"street":"15 bis rue Roger Salengro","zipCode":"92120","city":"MONTROUGE","country":{"code":"FR"}},"location":{"lat":48.8125031000000006997652235440909862518310546875,"lng":2.307387700000000041455905375187285244464874267578125},"description":[],"pass":{"key":"1Seance","shortDescription":"Recevez 1 s\u00e9ance d'essai GRATUITE","description":"Recevez votre s\u00e9ance d'essai GRATUITE par email !","free":true},"reviews":{"count":0,"avg":null},"openingHours":[],"products":[],"distance":1818,"services":[],"comforts":[],"equipments":[],"activities":[],"access":[]},{"id":8137,"name":"Pole-Holic","compte":"1","isSubscribed":false,"urls":{"long":"\/salle\/8137,pole-holic,ecole-de-danse,bagneux,92220,fr"},"searchPicture":{"url":"https:\/\/datas.masalledesport.com\/prod\/null"},"type":{"id":7,"name":"Ecole de danse"},"address":{"street":"13 rue Romain Rolland","zipCode":"92220","city":"BAGNEUX","country":{"code":"FR"}},"location":{"lat":48.8021585999999985006070346571505069732666015625,"lng":2.32252829999992993492696768953464925289154052734375},"description":[],"pass":{"key":"cours_gratuit","shortDescription":"Recevez 1 cours d'essai GRATUIT","description":"B\u00e9n\u00e9ficiez d'un cours d'essai gratuit !","free":true},"reviews":{"count":0,"avg":null},"openingHours":[],"products":[],"distance":1821,"services":[],"comforts":[],"equipments":[],"activities":[],"access":[]},{"id":3755,"name":"Eric Gym","compte":"1","isSubscribed":false,"urls":{"long":"\/salle\/3755,eric-gym,club-de-fitness,cachan,94230,fr"},"searchPicture":{"url":"https:\/\/datas.masalledesport.com\/prod\/null"},"type":{"id":1,"name":"Club de fitness"},"address":{"street":"21 avenue de le Division Leclerc","zipCode":"94230","city":"CACHAN","country":{"code":"FR"}},"location":{"lat":48.78508099999999814144757692702114582061767578125,"lng":2.328602000000000060708771343342959880828857421875},"description":[],"pass":{"key":"1Seance","shortDescription":"Recevez 1 s\u00e9ance d'essai GRATUITE","description":"Recevez votre s\u00e9ance d'essai GRATUITE par email !","free":true},"reviews":{"count":0,"avg":null},"openingHours":[],"products":[],"distance":1912,"services":[],"comforts":[],"equipments":[],"activities":[],"access":[]},{"id":6263,"name":"Moderne Swing","compte":"1","isSubscribed":false,"urls":{"long":"\/salle\/6263,moderne-swing,ecole-de-danse,montrouge,92120,fr"},"searchPicture":{"url":"https:\/\/datas.masalledesport.com\/prod\/null"},"type":{"id":7,"name":"Ecole de danse"},"address":{"street":"39 Rue Moli\u00e8re","zipCode":"92120","city":"MONTROUGE","country":{"code":"FR"}},"location":{"lat":48.81131719999999774017851450480520725250244140625,"lng":2.31374559999999984682972353766672313213348388671875},"description":[],"pass":{"key":"1Seance","shortDescription":"Recevez 1 s\u00e9ance d'essai GRATUITE","description":"Recevez votre s\u00e9ance d'essai GRATUITE par email !","free":true},"reviews":{"count":0,"avg":null},"openingHours":[],"products":[],"distance":1916,"services":[],"comforts":[],"equipments":[],"activities":[],"access":[]},{"id":4165,"name":"Set Studio Centre de Formation","compte":"1","isSubscribed":false,"urls":{"long":"\/salle\/4165,set-studio-centre-de-formation,ecole-de-danse,montrouge,92120,fr"},"searchPicture":{"url":"https:\/\/datas.masalledesport.com\/prod\/null"},"type":{"id":7,"name":"Ecole de danse"},"address":{"street":"63 rue Racine","zipCode":"92120","city":"MONTROUGE","country":{"code":"FR"}},"location":{"lat":48.81286300000000011323209037072956562042236328125,"lng":2.31237799999999982247800289769656956195831298828125},"description":[],"pass":{"key":"1Seance","shortDescription":"Recevez 1 s\u00e9ance d'essai GRATUITE","description":"Recevez votre s\u00e9ance d'essai GRATUITE par email !","free":true},"reviews":{"count":0,"avg":null},"openingHours":[],"products":[],"distance":1963,"services":[],"comforts":[],"equipments":[],"activities":[],"access":[]},{"id":9801,"name":"Ronan Gustin Coach Sportif Miha Bodytec","compte":"1","isSubscribed":false,"urls":{"long":"\/salle\/9801,ronan-gustin-coach-sportif-miha-bodytec,coach-sportif,montrouge,92120,fr"},"searchPicture":{"url":"https:\/\/datas.masalledesport.com\/prod\/null"},"type":{"id":8,"name":"Coach sportif"},"address":{"street":"103 avenue Verdier","zipCode":"92120","city":"MONTROUGE","country":{"code":"FR"}},"location":{"lat":48.81614090000000061309037846513092517852783203125,"lng":2.309488099999953192309476435184478759765625},"description":[],"pass":{"key":"1Seance","shortDescription":"Recevez 1 s\u00e9ance d'essai GRATUITE","description":"Recevez votre s\u00e9ance d'essai GRATUITE par email !","free":true},"reviews":{"count":0,"avg":null},"openingHours":[],"products":[],"distance":2084,"services":[],"comforts":[],"equipments":[],"activities":[],"access":[]},{"id":8553,"name":"Egocentrik","compte":"1","isSubscribed":false,"urls":{"long":"\/salle\/8553,egocentrik,centre-d-aquabike-aquabiking,montrouge,92120,fr"},"searchPicture":{"url":"https:\/\/datas.masalledesport.com\/prod\/place\/8553\/searchPicture\/1507294066442.jpeg","originalUrl":"picsData\/salles\/galeries\/8553-21617-800x600.jpg","imageProcess":"big-01"},"type":{"id":9,"name":"Centre d'Aquabike \/ Aquabiking"},"address":{"street":"78 avenue Verdier","zipCode":"92120","city":"MONTROUGE","country":{"code":"FR"}},"location":{"lat":48.8161649234965580035350285470485687255859375,"lng":2.3104506481323596744914539158344268798828125},"description":[],"pass":{"key":"autre","shortDescription":"B\u00e9n\u00e9ficiez de l'offre d\u00e9couverte","description":"1 s\u00e9ance d\u00e9couverte \u00e0 15\u20ac","free":false},"reviews":{"count":1,"avg":5},"openingHours":[],"products":[],"distance":2107,"services":[],"comforts":[],"equipments":[],"activities":[],"access":[]},{"id":2002,"name":"Alis\u00e9 Danse","compte":"1","isSubscribed":false,"urls":{"long":"\/salle\/2002,alise-danse,ecole-de-danse,montrouge,92120,fr"},"searchPicture":{"url":"https:\/\/datas.masalledesport.com\/prod\/null"},"type":{"id":7,"name":"Ecole de danse"},"address":{"street":"25bis avenue de la R\u00e9publique","zipCode":"92120","city":"MONTROUGE","country":{"code":"FR"}},"location":{"lat":48.81402849999999915553416940383613109588623046875,"lng":2.315727799999999891866764301084913313388824462890625},"description":[],"pass":{"key":"1Seance","shortDescription":"Recevez 1 s\u00e9ance d'essai GRATUITE","description":"Recevez votre s\u00e9ance d'essai GRATUITE par email !","free":true},"reviews":{"count":0,"avg":null},"openingHours":[],"products":[],"distance":2119,"services":[],"comforts":[],"equipments":[],"activities":[],"access":[]},{"id":9935,"name":"L'Orange Bleue Montrouge","compte":"1","isSubscribed":false,"urls":{"long":"\/salle\/9935,l-orange-bleue-montrouge,club-de-fitness,montrouge,92120,fr"},"searchPicture":{"url":"https:\/\/datas.masalledesport.com\/prod\/null"},"type":{"id":1,"name":"Club de fitness"},"address":{"street":"18 rue de saisset","zipCode":"92120","city":"MONTROUGE","country":{"code":"FR"}},"location":{"lat":48.81468319999999749825292383320629596710205078125,"lng":2.315067300000009709037840366363525390625},"description":[],"pass":{"key":"1Seance","shortDescription":"Recevez 1 s\u00e9ance d'essai GRATUITE","description":"Recevez votre s\u00e9ance d'essai GRATUITE par email !","free":true},"reviews":{"count":0,"avg":null},"openingHours":[],"products":[],"distance":2137,"services":[],"comforts":[],"equipments":[],"activities":[],"access":[]},{"id":4646,"name":"Chapala","compte":"1","isSubscribed":false,"urls":{"long":"\/salle\/4646,chapala,ecole-de-danse,arcueil,94110,fr"},"searchPicture":{"url":"https:\/\/datas.masalledesport.com\/prod\/null"},"type":{"id":7,"name":"Ecole de danse"},"address":{"street":"16-18 avenue Salvador Allend\u00e9","zipCode":"94110","city":"ARCUEIL","country":{"code":"FR"}},"location":{"lat":48.80364680000000277004801318980753421783447265625,"lng":2.331704400000000010351186574553139507770538330078125},"description":[],"pass":{"key":"1Seance","shortDescription":"Recevez 1 s\u00e9ance d'essai GRATUITE","description":"Recevez votre s\u00e9ance d'essai GRATUITE par email !","free":true},"reviews":{"count":0,"avg":null},"openingHours":[],"products":[],"distance":2240,"services":[],"comforts":[],"equipments":[],"activities":[],"access":[]},{"id":3697,"name":"Speedy Rock Club","compte":"1","isSubscribed":false,"urls":{"long":"\/salle\/3697,speedy-rock-club,ecole-de-danse,arcueil,94110,fr"},"searchPicture":{"url":"https:\/\/datas.masalledesport.com\/prod\/null"},"type":{"id":7,"name":"Ecole de danse"},"address":{"street":"27 rue Cl\u00e9ment Ader","zipCode":"94110","city":"ARCUEIL","country":{"code":"FR"}},"location":{"lat":48.80024569999999783931343699805438518524169921875,"lng":2.334196100000000217988826989312656223773956298828125},"description":[],"pass":{"key":"1Seance","shortDescription":"Recevez 1 s\u00e9ance d'essai GRATUITE","description":"Recevez votre s\u00e9ance d'essai GRATUITE par email !","free":true},"reviews":{"count":0,"avg":null},"openingHours":[],"products":[],"distance":2257,"services":[],"comforts":[],"equipments":[],"activities":[],"access":[]},{"id":928,"name":"Forest'Hill Meudon Val Fleuri","compte":"1","isSubscribed":false,"urls":{"long":"\/salle\/928,forest-hill-meudon-val-fleuri,club-de-fitness,meudon,92190,fr"},"searchPicture":{"url":"https:\/\/datas.masalledesport.com\/prod\/null"},"type":{"id":1,"name":"Club de fitness"},"address":{"street":"23 rue Charles Infroit","zipCode":"92190","city":"MEUDON","country":{"code":"FR"}},"location":{"lat":48.8065169999999994843165040947496891021728515625,"lng":2.24426900000000006940581442904658615589141845703125},"description":[],"pass":{"key":"1Seance","shortDescription":"Recevez 1 s\u00e9ance d'essai GRATUITE","description":"Recevez votre s\u00e9ance d'essai GRATUITE par email !","free":true},"reviews":{"count":0,"avg":null},"openingHours":[],"products":[],"distance":2268,"services":[],"comforts":[],"equipments":[],"activities":[],"access":[]},{"id":5334,"name":"L'Ecole de Danse","compte":"1","isSubscribed":false,"urls":{"long":"\/salle\/5334,l-ecole-de-danse,ecole-de-danse,arcueil,94110,fr"},"searchPicture":{"url":"https:\/\/datas.masalledesport.com\/prod\/null"},"type":{"id":7,"name":"Ecole de danse"},"address":{"street":"56 avenue Laplace","zipCode":"94110","city":"ARCUEIL","country":{"code":"FR"}},"location":{"lat":48.80912190000000094869392341934144496917724609375,"lng":2.330169300000000109918119051144458353519439697265625},"description":[],"pass":{"key":"1Seance","shortDescription":"Recevez 1 s\u00e9ance d'essai GRATUITE","description":"Recevez votre s\u00e9ance d'essai GRATUITE par email !","free":true},"reviews":{"count":0,"avg":null},"openingHours":[],"products":[],"distance":2368,"services":[],"comforts":[],"equipments":[],"activities":[],"access":[]},{"id":6517,"name":"Giga Zumba Arcueil","compte":"1","isSubscribed":false,"urls":{"long":"\/salle\/6517,giga-zumba-arcueil,salle-de-gym-bien-etre,arcueil,94110,fr"},"searchPicture":{"url":"https:\/\/datas.masalledesport.com\/prod\/null"},"type":{"id":4,"name":"Salle de gym \/ bien \u00eatre"},"address":{"street":"56 avenue Laplace","zipCode":"94110","city":"ARCUEIL","country":{"code":"FR"}},"location":{"lat":48.80912190000000094869392341934144496917724609375,"lng":2.330169300000000109918119051144458353519439697265625},"description":[],"pass":{"key":"1Seance","shortDescription":"Recevez 1 s\u00e9ance d'essai GRATUITE","description":"Recevez votre s\u00e9ance d'essai GRATUITE par email !","free":true},"reviews":{"count":0,"avg":null},"openingHours":[],"products":[],"distance":2368,"services":[],"comforts":[],"equipments":[],"activities":[],"access":[]},{"id":8483,"name":"Sun Sport Verri\u00e8res le Buisson","compte":"1","isSubscribed":false,"urls":{"long":"\/salle\/8483,sun-sport-verrieres-le-buisson,club-de-fitness,verrieres-le-buisson,91370,fr"},"searchPicture":{"url":"https:\/\/datas.masalledesport.com\/prod\/null"},"type":{"id":1,"name":"Club de fitness"},"address":{"street":"87 voie de Chatenay","zipCode":"91370","city":"VERRI\u00c8RES LE BUISSON","country":{"code":"FR"}},"location":{"lat":48.757377800000000434010871686041355133056640625,"lng":2.269077400000009792080390980117954313755035400390625},"description":[],"pass":{"key":"1Seance","shortDescription":"Recevez 1 s\u00e9ance d'essai GRATUITE","description":"Recevez votre s\u00e9ance d'essai GRATUITE par email !","free":true},"reviews":{"count":0,"avg":null},"openingHours":[],"products":[],"distance":2384,"services":[],"comforts":[],"equipments":[],"activities":[],"access":[]},{"id":9936,"name":"L'Orange Bleue Vanves","compte":"1","isSubscribed":false,"urls":{"long":"\/salle\/9936,l-orange-bleue-vanves,club-de-fitness,vanves,92170,fr"},"searchPicture":{"url":"https:\/\/datas.masalledesport.com\/prod\/null"},"type":{"id":1,"name":"Club de fitness"},"address":{"street":"68 avenue Victor Hugo","zipCode":"92170","city":"VANVES","country":{"code":"FR"}},"location":{"lat":48.82448000000000121190169011242687702178955078125,"lng":2.29087570000001505832187831401824951171875},"description":[],"pass":{"key":"1Seance","shortDescription":"Recevez 1 s\u00e9ance d'essai GRATUITE","description":"Recevez votre s\u00e9ance d'essai GRATUITE par email !","free":true},"reviews":{"count":0,"avg":null},"openingHours":[],"products":[],"distance":2402,"services":[],"comforts":[],"equipments":[],"activities":[],"access":[]}]}